manorender/__init__.py
manorender/cli.py
manorender-0.1.1.dist-info/METADATA
manorender-0.1.1.dist-info/WHEEL
manorender-0.1.1.dist-info/entry_points.txt
manorender-0.1.1.dist-info/top_level.txt
manorender-0.1.1.dist-info/RECORD
