Metadata-Version: 2.4
Name: manorender
Version: 0.1.1
Summary: Powerful 3D rendering engine with advanced features
Home-page: https://github.com/PlazmaDevelopment/manorender
Author: PlazmaDevelopment
Author-email: contact@plazmadev.com
Project-URL: Bug Reports, https://github.com/zubag/manorender/issues
Project-URL: Source, https://github.com/zubag/manorender
Project-URL: Documentation, https://manorender.readthedocs.io
Classifier: Development Status :: 4 - Beta
Classifier: Intended Audience :: Developers
Classifier: Intended Audience :: Science/Research
Classifier: License :: OSI Approved :: MIT License
Classifier: Programming Language :: Python :: 3
Classifier: Programming Language :: Python :: 3.7
Classifier: Programming Language :: Python :: 3.8
Classifier: Programming Language :: Python :: 3.9
Classifier: Programming Language :: Python :: 3.10
Classifier: Programming Language :: Python :: 3.11
Classifier: Operating System :: OS Independent
Classifier: Topic :: Scientific/Engineering :: Visualization
Classifier: Topic :: Software Development :: Libraries :: Python Modules
Requires-Python: >=3.7
Requires-Dist: numpy>=1.21.0
Requires-Dist: Pillow>=8.3.0
Requires-Dist: pythreejs>=2.3.0
Requires-Dist: scipy>=1.7.0
Requires-Dist: imageio>=2.9.0
Requires-Dist: PyOpenGL>=3.1.0
Requires-Dist: PyGLM>=1.7.0
Provides-Extra: dev
Requires-Dist: pytest>=6.2.0; extra == "dev"
Requires-Dist: pytest-cov>=2.12.0; extra == "dev"
Requires-Dist: black>=21.5b0; extra == "dev"
Requires-Dist: isort>=5.9.0; extra == "dev"
Requires-Dist: flake8>=3.9.0; extra == "dev"
Requires-Dist: mypy>=0.812; extra == "dev"
Provides-Extra: docs
Requires-Dist: sphinx>=4.0.0; extra == "docs"
Requires-Dist: sphinx-rtd-theme>=0.5.0; extra == "docs"
Requires-Dist: sphinx-autodoc-typehints>=1.12.0; extra == "docs"
Dynamic: author
Dynamic: author-email
Dynamic: classifier
Dynamic: description
Dynamic: description-content-type
Dynamic: home-page
Dynamic: project-url
Dynamic: provides-extra
Dynamic: requires-dist
Dynamic: requires-python
Dynamic: summary
